[{"id": 0, "title": "Ulf Kristersson om omr\u00f6stningen i riksdagen", "date": "Mon, 5 Nov 2018 10:54:37 +0100"}, {"id": 1, "title": "Jimmie \u00c5kesson: Kristersson m\u00e5ste ge oss garantier f\u00f6r st\u00f6d", "date": "Mon, 5 Nov 2018 10:37:35 +0100"}, {"id": 2, "title": "Mordf\u00f6rs\u00f6k i Kramfors \u2013 man misshandlad med tillhygge", "date": "Mon, 5 Nov 2018 10:03:56 +0100"}, {"id": 3, "title": "R\u00f6kutveckling p\u00e5 X2000-t\u00e5g", "date": "Mon, 5 Nov 2018 09:57:58 +0100"}, {"id": 4, "title": "Talmannens besked: L\u00e5t riksdagen r\u00f6sta om Ulf Kristersson som statsminister", "date": "Mon, 5 Nov 2018 09:35:48 +0100"}]